aspose/cells/py.typed
aspose/pycore/py.typed
aspose/pycore/__init__.pyi
aspose/pyreflection/py.typed
aspose/pyreflection/__init__.pyi
aspose/pydrawing/py.typed
aspose/pydrawing/__init__.pyi
aspose/pydrawing/design.pyi
aspose/pydrawing/drawing2d.pyi
aspose/pydrawing/imaging.pyi
aspose/pydrawing/printing.pyi
aspose/pydrawing/text.pyi
aspose/cells/__init__.pyi
aspose/cells/charts/__init__.pyi
aspose/cells/datamodels/__init__.pyi
aspose/cells/digitalsignatures/__init__.pyi
aspose/cells/drawing/__init__.pyi
aspose/cells/drawing/activexcontrols/__init__.pyi
aspose/cells/drawing/equations/__init__.pyi
aspose/cells/drawing/texts/__init__.pyi
aspose/cells/externalconnections/__init__.pyi
aspose/cells/json/__init__.pyi
aspose/cells/loading/__init__.pyi
aspose/cells/lowcode/__init__.pyi
aspose/cells/markdown/__init__.pyi
aspose/cells/markup/__init__.pyi
aspose/cells/metadata/__init__.pyi
aspose/cells/metas/__init__.pyi
aspose/cells/numbers/__init__.pyi
aspose/cells/ods/__init__.pyi
aspose/cells/pivot/__init__.pyi
aspose/cells/properties/__init__.pyi
aspose/cells/querytables/__init__.pyi
aspose/cells/rendering/__init__.pyi
aspose/cells/rendering/pdfsecurity/__init__.pyi
aspose/cells/revisions/__init__.pyi
aspose/cells/saving/__init__.pyi
aspose/cells/settings/__init__.pyi
aspose/cells/slicers/__init__.pyi
aspose/cells/slides/__init__.pyi
aspose/cells/tables/__init__.pyi
aspose/cells/timelines/__init__.pyi
aspose/cells/utility/__init__.pyi
aspose/cells/vba/__init__.pyi
aspose/cells/webextensions/__init__.pyi
.__pyi_patched
aspose/__init__.py
aspose/cells.cpython-310-darwin.so
aspose/cells.cpython-311-darwin.so
aspose/cells.cpython-312-darwin.so
aspose/cells.cpython-313-darwin.so
aspose/cells.cpython-38-darwin.so
aspose/cells.cpython-39-darwin.so
aspose/pycore.cpython-310-darwin.so
aspose/pycore.cpython-311-darwin.so
aspose/pycore.cpython-312-darwin.so
aspose/pycore.cpython-313-darwin.so
aspose/pycore.cpython-38-darwin.so
aspose/pycore.cpython-39-darwin.so
aspose_cells_python-25.11.0.dist-info/METADATA
aspose_cells_python-25.11.0.dist-info/WHEEL
aspose_cells_python-25.11.0.dist-info/entry_points.txt
aspose_cells_python-25.11.0.dist-info/top_level.txt
aspose_cells_python-25.11.0.dist-info/RECORD