Metadata-Version: 2.1
Name: aspose-cells-python
Version: 25.11.0
Summary: Aspose.Cells for Python via .NET is a powerful and efficient library for working with Excel files in Python. It supports a wide range of spreadsheet formats including XLS, XLSX, XLSB, ODS, CSV, and HTML, enabling you to programmatically manipulate and convert files with ease. The library also comes with free support.
Home-page: https://products.aspose.com/cells/
Author: aspose-cells
License: https://company.aspose.com/legal/eula
Project-URL: API Reference, https://reference.aspose.com/cells/python-net/
Project-URL: Docs, https://docs.aspose.com/cells/python-net/
Project-URL: Release Notes, https://releases.aspose.com/cells/python-net/release-notes/2025/aspose-cells-for-python-net-25-11-release-notes/
Project-URL: Blog, https://blog.aspose.com/category/cells/
Project-URL: Free Support, https://forum.aspose.com/c/cells/
Project-URL: Temporary License, https://purchase.aspose.com/temporary-license/
Keywords: Excel,XLS,XLSX,XLSB,CSV,PDF,JPG,PNG,HTML,ODS,Numbers,XLSM,OOXML,Spreadsheet,Markdown,XPS,DOCX,PPTX,MHTML,TXT,JSON,SVG,EMF,TIFF
Platform: macos_arm64
Classifier: Intended Audience :: Developers
Classifier: Intended Audience :: Education
Classifier: Intended Audience :: Manufacturing
Classifier: Intended Audience :: Science/Research
Classifier: Operating System :: Microsoft :: Windows
Classifier: Operating System :: POSIX :: Linux
Classifier: Operating System :: Unix
Classifier: Operating System :: MacOS :: MacOS X
Classifier: License :: Free To Use But Restricted
Classifier: License :: Other/Proprietary License
Classifier: Programming Language :: Python :: 3.8
Classifier: Programming Language :: Python :: 3.9
Classifier: Programming Language :: Python :: 3.10
Classifier: Programming Language :: Python :: 3.11
Classifier: Programming Language :: Python :: 3.12
Classifier: Programming Language :: Python :: 3.13
Classifier: Topic :: Software Development :: Libraries
Requires-Python: >=3.8,<3.14
